naver_rank_bot/__init__.py
naver_rank_bot/bot.py
naver_rank_bot/config.py
naver_rank_bot/js_evaluator.py
naver_rank_bot/py.typed
naver_rank_bot-0.1.20.dist-info/licenses/LICENSE
naver_rank_bot-0.1.20.dist-info/METADATA
naver_rank_bot-0.1.20.dist-info/WHEEL
naver_rank_bot-0.1.20.dist-info/top_level.txt
naver_rank_bot-0.1.20.dist-info/RECORD
