Metadata-Version: 2.4
Name: naver-rank-bot
Version: 0.1.20
Summary: NoDriver-based browser automation tool for Naver SmartStore product ranking analysis
Author-email: Benjamin Lee <ibank21@gmail.com>
License: AGPL-3.0-or-later
Project-URL: Homepage, https://github.com/marqetly/naver-rank-bot
Project-URL: Documentation, https://github.com/marqetly/naver-rank-bot#readme
Project-URL: Repository, https://github.com/marqetly/naver-rank-bot
Project-URL: Issues, https://github.com/marqetly/naver-rank-bot/issues
Keywords: naver,smartstore,bot,scraping,nodriver,ranking
Classifier: Development Status :: 4 - Beta
Classifier: Intended Audience :: Developers
Classifier: License :: OSI Approved :: GNU Affero General Public License v3 or later (AGPLv3+)
Classifier: Programming Language :: Python :: 3
Classifier: Programming Language :: Python :: 3.11
Classifier: Programming Language :: Python :: 3.12
Classifier: Programming Language :: Python :: 3.13
Classifier: Programming Language :: Python :: 3.14
Classifier: Topic :: Software Development :: Libraries :: Python Modules
Requires-Python: >=3.11
License-File: LICENSE
Requires-Dist: nodriver>=0.35.0
Provides-Extra: dev
Requires-Dist: pytest>=7.0.0; extra == "dev"
Requires-Dist: pytest-asyncio>=0.21.0; extra == "dev"
Dynamic: license-file
